full_adder_test/full_adder_test.vhd
library ieee;
use ieee.std_logic_1164.all;

entity full_adder_test is
port( a,b,c: in std_logic;
	sum,ca: out std_logic
	);
end full_adder_test;

architecture rtl1 of full_adder_test is 

signal S1, S2, S3: std_logic;
begin

		s1      <= ( a XOR b );       --after 15 ns; 
		s2      <= ( c AND s1 ); 	 --after 5 ns; 
		s3      <= ( a AND b );       --after 5 ns; 	

--PROCESS(clk)
--		BEGIN
--		IF clk'EVENT AND clk = '1' THEN
			
		Sum  	<= ( s1 XOR c )	;	 --after 15 ns; 
		ca	 	<= ( s2 OR s3 );      --after 5 ns;
--		end if;
--		end process;
end rtl1;

add_mm/add_mm.vhd
library ieee;
use ieee.std_logic_1164.all;

entity add_mm is
  port (a		: in std_logic_vector(3 downto 0);
		c		: in std_logic_vector(3 downto 0);
		b 		: in std_logic_vector(1 downto 0);
		d 		: in std_logic_vector(1 downto 0);
		p		: out std_logic_vector(5 downto 0));
  end add_mm;
	  
architecture add_rtl of add_mm is

component full_adder_test is
  port( a,b,c	: in std_logic;
		ca,sum	: out std_logic
	);
  end component;
  
--component half_adder_test is
--  port( a,b 	:in std_logic;
--	ca,sum		: out std_logic
--	);
--  end component;
    
signal cat, st 		: std_logic_vector (7 downto 0);
signal ab0, ab1		: std_logic_vector (3 downto 0);

begin



ab0(0) <= a(0) and b(0);
ab0(1) <= a(1) and b(0);
ab0(2) <= a(2) and b(0);
ab0(3) <= a(3) and b(0);

ab1(0) <= a(0) and b(1);
ab1(1) <= a(1) and b(1);
ab1(2) <= a(2) and b(1);
ab1(3) <= a(3) and b(1);

fa1: full_adder_test port map(ab0(0),d(0),  c(0),  cat(0),st(0));
fa2: full_adder_test port map(ab0(1),ab1(0),c(1),  cat(1),st(1)); 
fa3: full_adder_test port map(ab0(2),ab1(1),c(2),  cat(2),st(2)); 
fa4: full_adder_test port map(ab0(3),ab1(2),c(3),  cat(3),st(3)); 
fa5: full_adder_test port map(st(1) ,cat(0),d(1),  cat(4),st(4)); 
fa6: full_adder_test port map(st(2) ,cat(1),cat(4),cat(5),st(5)); 
fa7: full_adder_test port map(st(3), cat(2),cat(5),cat(6),st(6));
fa8: full_adder_test port map(ab1(3),cat(3),cat(6),cat(7),st(7));


P(0) <= st(0); 
p(1) <= st(4);
p(2) <= st(5);
p(3) <= st(6);
p(4) <= st(7);
p(5) <= cat(7);



end add_rtl;

Latch_D/latch_d.vhd
library IEEE;
use IEEE.STD_LOGIC_1164.ALL;

entity latch_d is
    Port ( D  : in  STD_LOGIC_vector(5 downto 0);
           EN : in  STD_LOGIC;
           Q  : out STD_LOGIC_vector(5 downto 0));
end latch_d;

architecture Behavioral of latch_d is
    signal DATA : STD_LOGIC;
    signal zero : std_logic_vector(5 downto 0);
begin
	
	process(D, EN)
    begin

        -- clock rising edge

	if (EN='1' and EN'event) then
	    Q <= D;
	end if;

    end process;
	
end Behavioral;

latch_88amm/latch_88amm.vhd
-- using latch --

library ieee;
use ieee.std_logic_1164.all;

entity latch_88amm is
port( clk: in std_logic;
	  x	: in std_logic_vector(7  downto 0);
	  y	: in std_logic_vector(7  downto 0);
	  c : in std_logic_vector(7  downto 0);
	  d	: in std_logic_vector(7  downto 0);
	  tp : out std_logic_vector(15 downto 0));
	  
end latch_88amm;
				
architecture amm_rtl of latch_88amm is
  		
component add_mm is
port (	a		: in std_logic_vector(3 downto 0);
		c		: in std_logic_vector(3 downto 0);
		b 		: in std_logic_vector(1 downto 0);
		d 		: in std_logic_vector(1 downto 0);
		p		:out std_logic_vector(5 downto 0));
  end component;
  
component latch_d is
port (  D  : in  STD_LOGIC_vector(5 downto 0);
        EN : in  STD_LOGIC;
        Q  : out STD_LOGIC_vector(5 downto 0));
	end component;
	  


	  
signal 	pl,ph		: std_logic_vector(23 downto 0);
signal  p			: std_logic_vector(15  downto 0);
signal  tc		: std_logic_vector(15 downto 0);
signal  p1,p2,p3,p4,p5,p6: std_logic_vector(5 downto 0);
signal clk_p : STD_LOGIC;
signal zero : std_logic;

begin

--	Temp New Clk
--		zero <= '0';
--    clk_p <= '1' when (clk = '0') else zero ;
	
	
	
	amm1 : add_mm port map(x(3 downto 0), c(3 downto 0),		 y(1 downto 0), d(1 downto 0),				p1(5 downto 0));
	L1	 : latch_d port map(p1(5 downto 0),clk,pl(5 downto 0));
	
	amm2 : add_mm port map(x(7 downto 4), c(7 downto 4),		 y(1 downto 0), pl(5 downto 4),		p2(5 downto 0));
	L2	 : latch_d port map(p2(5 downto 0),clk,ph(5 downto 0));	
	
	tc(3 downto 2) <= ph(1 downto 0);	
	tc(1 downto 0) <= pl(3 downto 2);

	amm3 : add_mm port map(x(3 downto 0), tc(3 downto 0),y(3 downto 2), d(3 downto 2),			 	p3(5 downto 0));
	L3	 : latch_d port map(p3(5 downto 0),clk,pl(11 downto 6));	


	amm4 : add_mm port map(x(7 downto 4), ph(5 downto 2),y(3 downto 2), pl(11 downto 10),	p4(5 downto 0));
	L4	 : latch_d port map(p4(5 downto 0),clk,ph(11 downto 6));

	tc(5 downto 4) <= pl(9 downto 8);	
	tc(7 downto 6) <= ph(7 downto 6);
	
	amm5 : add_mm port map(x(3 downto 0), tc(7 downto 4),y(5 downto 4), d(5 downto 4),				p5(5 downto 0));
	L5	 : latch_d port map(p5(5 downto 0),clk,pl(17 downto 12));

	amm6 : add_mm port map(x(7 downto 4), ph(11 downto 8),y(5 downto 4), pl(17 downto 16),	p6(5 downto 0));
	L6	 : latch_d port map(p6(5 downto 0),clk,ph(17 downto 12));
	
	tc(9 downto 8) <= pl(15 downto 14);
	tc(11 downto 10)<= ph(13 downto 12);
	
	amm7 : add_mm port map(x(3 downto 0), tc(11 downto 8),y(7 downto 6), d(7 downto 6),				pl(23 downto 18));	

	amm8 : add_mm port map(x(7 downto 4), ph(17 downto 14),y(7 downto 6),pl(23 downto 22),	ph(23 downto 18));
	
	
		tp(1 downto 0)	<=	pl(1 downto 0);
		tp(3 downto 2)	<=	pl(7 downto 6);
		tp(5 downto 4)	<=	pl(13 downto 12);
		tp(9 downto 6)	<=	pl(21 downto 18);
		tp(15 downto 10)	<=  ph(23 downto 18);

	
	
	

end amm_rtl;

latch_88amm/latch_88amm.vcd
$comment
Copyright (C) 1991-2009 Altera Corporation
Your use of Altera Corporation's design tools, logic functions 
and other software and tools, and its AMPP partner logic 
functions, and any output files from any of the foregoing 
(including device programming or simulation files), and any 
associated documentation or information are expressly subject 
to the terms and conditions of the Altera Program License 
Subscription Agreement, Altera MegaCore Function License 
Agreement, or other applicable license agreement, including, 
without limitation, that your use is for the sole purpose of 
programming logic devices manufactured by Altera and sold by 
Altera or its authorized distributors.  Please refer to the 
applicable agreement for further details.
$end

$date 
  05/07/2016 01:17:42 
$end
$version 
 QUARTUS_VCD_EXPORT 1.0 
$end
$timescale
  1 ps
$end
$scope module latch_88amm $end
$var reg 1 ! clk $end
$var reg 8 " x[7:0] $end
$var reg 8 # y[7:0] $end
$var reg 16 $ tp[15:0] $end
$var reg 8 % c[7:0] $end
$var reg 8 & d[7:0] $end
$upscope $end
$enddefinitions $end
#0
$dumpvars
1!
b11111111 "
b11111111 #
b1011111101000000 $
b0 %
b0 &
$end
#10000
0!
#20000
1!
#25731
b1011111101000100 $
#25765
b1011111101010100 $
#26243
b1011111001010100 $
#26327
b1011111001010101 $
#26390
b1011111011010101 $
#26479
b1111111011010101 $
#26485
b1111111010010101 $
#26670
b1101111010010101 $
#26957
b1101110010010101 $
#26980
b1101110000010101 $
#27646
b1100110000010101 $
#27733
b1100110100010101 $
#28104
b1100100100010101 $
#28274
b1110100100010101 $
#29456
b1110110100010101 $
#30000
0!
#40000
1!
#45731
b1110110100010001 $
#45765
b1110110100000001 $
#46243
b1110110000000001 $
#46390
b1110110010000001 $
#46665
b1111110010000001 $
#46666
b1111111010000001 $
#47014
b1111111110000001 $
#47714
b1111110110000001 $
#48104
b1111100110000001 $
#50000
0!
#60000
1!
#65503
b1111100110100001 $
#68104
b1111110110100001 $
#70000
0!
#80000
1!
#85503
b1111110110000001 $
#86390
b1111110100000001 $
#87014
b1111110000000001 $
#87714
b1111111000000001 $
#90000
0!
#100000
1!
#110000
0!
#120000
1!
b11100011 "
b11100011 #
#128737
b1111011000000001 $
#128742
b1111011100000001 $
#129749
b1111001100000001 $
#130000
0!
#130121
b1111101100000001 $
#130162
b1111100100000001 $
#131534
b1110100100000001 $
#140000
1!
#145731
b1110100100000101 $
#145765
b1110100100010101 $
#145989
b1110100100011101 $
#146243
b1110100000011101 $
#146390
b1110100010011101 $
#146665
b1111100010011101 $
#146666
b1111101010011101 $
#147014
b1111101110011101 $
#147036
b1111001110011101 $
#147292
b1101001110011101 $
#148232
b1101101110011101 $
#148621
b1101001110011101 $
#148628
b1101011110011101 $
#149824
b1101001110011101 $
#150000
0!
#150213
b1101011110011101 $
#160000
1!
#165731
b1101011110011001 $
#166217
b1101111110011001 $
#166243
b1101111010011001 $
#166485
b1101111011011001 $
#166957
b1101110011011001 $
#166980
b1101110001011001 $
#167169
b1100110001011001 $
#167511
b1100111001011001 $
#168104
b1100101001011001 $
#169456
b1100111001011001 $
#169824
b1100101001011001 $
#170000
0!
#180000
1!
#185503
b1100101001111001 $
#185765
b1100101001101001 $
#186217
b1100001001101001 $
#186243
b1100001101101001 $
#186479
b1000001101101001 $
#186665
b1001001101101001 $
#186666
b1001000101101001 $
#186670
b1011000101101001 $
#186957
b1011001101101001 $
#187036
b1011101101101001 $
#187169
b1010101101101001 $
#187511
b1010100101101001 $
#187586
b1110100101101001 $
#187763
b1100100101101001 $
#187864
b1100000101101001 $
#188104
b1100010101101001 $
#188232
b1100110101101001 $
#188628
b1100100101101001 $
#189456
b1100110101101001 $
#189824
b1100100101101001 $
#190000
0!
#200000
1!
#205503
b1100100101001001 $
#210000
0!
#220000
1!
#230000
0!
#240000
1!
b11111111 "
b11111111 #
#248737
b1100000101001001 $
#248742
b1100000001001001 $
#249143
b1100100001001001 $
#249749
b1100110001001001 $
#250000
0!
#250150
b1101110001001001 $
#250162
b1101111001001001 $
#250842
b1101101001001001 $
#251396
b1101111001001001 $
#251952
b1101101001001001 $
#252217
b1101111001001001 $
#260000
1!
#265503
b1101111001101001 $
#265731
b1101111001101101 $
#265765
b1101111001111101 $
#266217
b1101011001111101 $
#266243
b1101011101111101 $
#266485
b1101011100111101 $
#266666
b1101010100111101 $
#266670
b1111010100111101 $
#266957
b1111011100111101 $
#266980
b1111011110111101 $
#267864
b1111111110111101 $
#268104
b1111101110111101 $
#269278
b1110101110111101 $
#269456
b1110111110111101 $
#270000
0!
#280000
1!
#285731
b1110111110111001 $
#285765
b1110111110101001 $
#285989
b1110111110100001 $
#286243
b1110111010100001 $
#286390
b1110111000100001 $
#286485
b1110111001100001 $
#286957
b1110110001100001 $
#286980
b1110110011100001 $
#287014
b1110110111100001 $
#287646
b1111110111100001 $
#287733
b1111110011100001 $
#288104
b1111100011100001 $
#289456
b1111110011100001 $
#290000
0!
#300000
1!
#306243
b1111110111100001 $
#306666
b1111111111100001 $
#306957
b1111110111100001 $
#310000
0!
#320000
1!
#325503
b1111110111000001 $
#326485
b1111110110000001 $
#326980
b1111110100000001 $
#327733
b1111110000000001 $
#328433
b1111111000000001 $
